stockly_python_common/__init__.py
stockly_python_common/client.py
stockly_python_common/query.py
stockly_python_common/static.py
stockly_python_common/stockly_messaging.py
stockly_python_common/stockly_utils.py
stockly_python_common-0.1.dist-info/LICENSE.txt
stockly_python_common-0.1.dist-info/METADATA
stockly_python_common-0.1.dist-info/WHEEL
stockly_python_common-0.1.dist-info/top_level.txt
stockly_python_common-0.1.dist-info/RECORD
